ais_dagger_agents_config/__init__.py
ais_dagger_agents_config/models.py
ais_dagger_agents_config-0.1.25.dist-info/METADATA
ais_dagger_agents_config-0.1.25.dist-info/WHEEL
ais_dagger_agents_config-0.1.25.dist-info/licenses/LICENSE
ais_dagger_agents_config-0.1.25.dist-info/RECORD
